BCSFE_Python/__init__.py
BCSFE_Python/__main__.py
BCSFE_Python/adb_handler.py
BCSFE_Python/config_manager.py
BCSFE_Python/csv_handler.py
BCSFE_Python/encyrpt.py
BCSFE_Python/feature_handler.py
BCSFE_Python/game_data_getter.py
BCSFE_Python/helper.py
BCSFE_Python/item.py
BCSFE_Python/locale_handler.py
BCSFE_Python/managed_item.py
BCSFE_Python/parse_save.py
BCSFE_Python/patcher.py
BCSFE_Python/py.typed
BCSFE_Python/record_handler.py
BCSFE_Python/root_handler.py
BCSFE_Python/serialise_save.py
BCSFE_Python/server_handler.py
BCSFE_Python/updater.py
BCSFE_Python/user_info.py
BCSFE_Python/user_input_handler.py
BCSFE_Python/edits/__init__.py
BCSFE_Python/edits/basic/__init__.py
BCSFE_Python/edits/basic/basic_items.py
BCSFE_Python/edits/basic/catfruit.py
BCSFE_Python/edits/basic/catseyes.py
BCSFE_Python/edits/basic/ototo_base_mats.py
BCSFE_Python/edits/basic/talent_orbs.py
BCSFE_Python/edits/basic/talent_orbs_new.py
BCSFE_Python/edits/cats/__init__.py
BCSFE_Python/edits/cats/cat_helper.py
BCSFE_Python/edits/cats/cat_id_selector.py
BCSFE_Python/edits/cats/chara_drop.py
BCSFE_Python/edits/cats/clear_cat_guide.py
BCSFE_Python/edits/cats/evolve_cats.py
BCSFE_Python/edits/cats/get_remove_cats.py
BCSFE_Python/edits/cats/talents.py
BCSFE_Python/edits/cats/upgrade_blue.py
BCSFE_Python/edits/cats/upgrade_cats.py
BCSFE_Python/edits/gamototo/__init__.py
BCSFE_Python/edits/gamototo/fix_gamatoto.py
BCSFE_Python/edits/gamototo/gamatoto_xp.py
BCSFE_Python/edits/gamototo/helpers.py
BCSFE_Python/edits/gamototo/ototo_cat_cannon.py
BCSFE_Python/edits/levels/__init__.py
BCSFE_Python/edits/levels/aku.py
BCSFE_Python/edits/levels/allow_filibuster_clearing.py
BCSFE_Python/edits/levels/behemoth_culling.py
BCSFE_Python/edits/levels/clear_tutorial.py
BCSFE_Python/edits/levels/enigma_stages.py
BCSFE_Python/edits/levels/event_stages.py
BCSFE_Python/edits/levels/gauntlet.py
BCSFE_Python/edits/levels/itf_timed_scores.py
BCSFE_Python/edits/levels/legend_quest.py
BCSFE_Python/edits/levels/main_story.py
battlecatscarlos-0.0.0.8.dist-info/LICENSE
battlecatscarlos-0.0.0.8.dist-info/METADATA
battlecatscarlos-0.0.0.8.dist-info/WHEEL
battlecatscarlos-0.0.0.8.dist-info/top_level.txt
battlecatscarlos-0.0.0.8.dist-info/RECORD
