Metadata-Version: 2.1
Name: battlecatscarlos
Version: 0.0.0.8
Summary: A battle cats save file editor
Home-page: https://github.com/carlostmgps
Author: CarlosCheung
Classifier: Programming Language :: Python :: 3
Classifier: License :: OSI Approved :: MIT License
Classifier: Operating System :: OS Independent
Requires-Python: >=3.9
License-File: LICENSE
Requires-Dist: colored ==1.4.4
Requires-Dist: tk
Requires-Dist: python-dateutil
Requires-Dist: requests
Requires-Dist: pyyaml
Provides-Extra: testing
Requires-Dist: pytest ; extra == 'testing'
Requires-Dist: pytest-cov ; extra == 'testing'
